ros_tracetools-8.2.4.data/data/include/tracetools/tracetools/config.h
ros_tracetools-8.2.4.data/data/include/tracetools/tracetools/status.h
ros_tracetools-8.2.4.data/data/include/tracetools/tracetools/tp_call.h
ros_tracetools-8.2.4.data/data/include/tracetools/tracetools/tracetools.h
ros_tracetools-8.2.4.data/data/include/tracetools/tracetools/utils.hpp
ros_tracetools-8.2.4.data/data/include/tracetools/tracetools/version.h
ros_tracetools-8.2.4.data/data/include/tracetools/tracetools/visibility_control.hpp
ros_tracetools-8.2.4.data/data/lib/libtracetools.so
ros_tracetools-8.2.4.data/data/lib/libtracetools_status.so
ros_tracetools-8.2.4.data/data/lib/tracetools/status
ros_tracetools-8.2.4.data/data/share/ament_index/resource_index/package_run_dependencies/tracetools
ros_tracetools-8.2.4.data/data/share/ament_index/resource_index/packages/tracetools
ros_tracetools-8.2.4.data/data/share/ament_index/resource_index/parent_prefix_path/tracetools
ros_tracetools-8.2.4.data/data/share/tracetools/local_setup.bash
ros_tracetools-8.2.4.data/data/share/tracetools/local_setup.dsv
ros_tracetools-8.2.4.data/data/share/tracetools/local_setup.sh
ros_tracetools-8.2.4.data/data/share/tracetools/local_setup.zsh
ros_tracetools-8.2.4.data/data/share/tracetools/package.dsv
ros_tracetools-8.2.4.data/data/share/tracetools/package.xml
ros_tracetools-8.2.4.data/data/share/tracetools/cmake/ament_cmake_export_include_directories-extras.cmake
ros_tracetools-8.2.4.data/data/share/tracetools/cmake/ament_cmake_export_libraries-extras.cmake
ros_tracetools-8.2.4.data/data/share/tracetools/cmake/ament_cmake_export_link_flags-extras.cmake
ros_tracetools-8.2.4.data/data/share/tracetools/cmake/ament_cmake_export_targets-extras.cmake
ros_tracetools-8.2.4.data/data/share/tracetools/cmake/tracetoolsConfig-version.cmake
ros_tracetools-8.2.4.data/data/share/tracetools/cmake/tracetoolsConfig.cmake
ros_tracetools-8.2.4.dist-info/METADATA
ros_tracetools-8.2.4.dist-info/WHEEL
ros_tracetools-8.2.4.dist-info/top_level.txt
ros_tracetools-8.2.4.dist-info/RECORD
