Metadata-Version: 2.4
Name: ros-tracetools
Version: 8.2.4
Summary: Wheel for the tracetools (ros-tracetools) ROS 2 package.
Dynamic: description
Dynamic: description-content-type
Dynamic: summary
